keras_crf/__init__.py
keras_crf/crf_model.py
tests/__init__.py
tests/crf_model_test.py
keras_crf-0.3.0.dist-info/LICENSE
keras_crf-0.3.0.dist-info/METADATA
keras_crf-0.3.0.dist-info/WHEEL
keras_crf-0.3.0.dist-info/top_level.txt
keras_crf-0.3.0.dist-info/RECORD
