Metadata-Version: 2.1
Name: keras-crf
Version: 0.3.0
Summary: A more elegant and convenient CRF built on tensorflow-addons.
Home-page: https://github.com/luozhouyang/keras-crf
Author: ZhouYang Luo
Author-email: zhouyang.luo@gmail.com
License: Apache Software License
Platform: UNKNOWN
Classifier: Programming Language :: Python :: 3
Classifier: Programming Language :: Python :: 3.6
Classifier: Programming Language :: Python :: 3.7
Classifier: Programming Language :: Python :: 3.8
Classifier: License :: OSI Approved :: Apache Software License
Classifier: Operating System :: OS Independent
Classifier: Topic :: Scientific/Engineering :: Artificial Intelligence
Requires-Dist: tensorflow
Requires-Dist: tensorflow-addons
